pywaves/ParallelPyWaves.py
pywaves/WXFeeCalculator.py
pywaves/__init__.py
pywaves/address.py
pywaves/asset.py
pywaves/contract.py
pywaves/crypto.py
pywaves/oracle.py
pywaves/order.py
pywaves/txGenerator.py
pywaves/txSigner.py
pywaves_ce-2.0.3.dist-info/METADATA
pywaves_ce-2.0.3.dist-info/WHEEL
pywaves_ce-2.0.3.dist-info/licenses/LICENSE
pywaves_ce-2.0.3.dist-info/RECORD
