Metadata-Version: 2.4
Name: PyWaves-CE
Version: 2.0.3
Summary: Python library for interacting with the Waves blockchain
License-File: LICENSE
Author: PyWaves Contributors
Requires-Python: >=3.8,<4.0
Classifier: License :: OSI Approved :: MIT License
Classifier: Operating System :: OS Independent
Classifier: Programming Language :: Python :: 3
Classifier: Programming Language :: Python :: 3.8
Classifier: Programming Language :: Python :: 3.9
Classifier: Programming Language :: Python :: 3.10
Classifier: Programming Language :: Python :: 3.11
Classifier: Programming Language :: Python :: 3.12
Classifier: Programming Language :: Python :: 3.13
Classifier: Programming Language :: Python :: 3.14
Requires-Dist: base58 (>=2.1.1,<3.0.0)
Requires-Dist: pywaves-curve25519 (>=1.0.4,<2.0.0)
Requires-Dist: pywaves-protobuf (>=1.5.2,<2.0.0)
Requires-Dist: requests (>=2.32.3,<3.0.0)
